e3sm_quickview/__init__.py
e3sm_quickview/app.py
e3sm_quickview/pipeline.py
e3sm_quickview/view_manager.py
e3sm_quickview/assets/__init__.py
e3sm_quickview/assets/banner.jpg
e3sm_quickview/assets/icon-192.png
e3sm_quickview/assets/icon-full.png
e3sm_quickview/assets/quick-view-text.png
e3sm_quickview/assets/small-icon.png
e3sm_quickview/components/__init__.py
e3sm_quickview/components/css.py
e3sm_quickview/components/dialogs.py
e3sm_quickview/components/doc.py
e3sm_quickview/components/drawers.py
e3sm_quickview/components/file_browser.py
e3sm_quickview/components/toolbars.py
e3sm_quickview/components/tools.py
e3sm_quickview/components/view.py
e3sm_quickview/data/connectivity.nc
e3sm_quickview/data/globe.vtk
e3sm_quickview/module/__init__.py
e3sm_quickview/module/serve/utils.js
e3sm_quickview/plugins/eam_filters.py
e3sm_quickview/plugins/eam_gridlines.py
e3sm_quickview/plugins/eam_projection.py
e3sm_quickview/plugins/eam_reader.py
e3sm_quickview/presets/__init__.py
e3sm_quickview/presets/acton_PARAVIEW.xml
e3sm_quickview/presets/bam_PARAVIEW.xml
e3sm_quickview/presets/batlow_PARAVIEW.xml
e3sm_quickview/presets/berlin_PARAVIEW.xml
e3sm_quickview/presets/davos_PARAVIEW.xml
e3sm_quickview/presets/grayC_PARAVIEW.xml
e3sm_quickview/presets/lajolla_PARAVIEW.xml
e3sm_quickview/presets/lisbon_PARAVIEW.xml
e3sm_quickview/presets/managua_PARAVIEW.xml
e3sm_quickview/presets/navia_PARAVIEW.xml
e3sm_quickview/presets/oslo_PARAVIEW.xml
e3sm_quickview/presets/roma_PARAVIEW.xml
e3sm_quickview/presets/tokyo_PARAVIEW.xml
e3sm_quickview/presets/vanimo_PARAVIEW.xml
e3sm_quickview/presets/vik_PARAVIEW.xml
e3sm_quickview/utils/__init__.py
e3sm_quickview/utils/cli.py
e3sm_quickview/utils/color.py
e3sm_quickview/utils/colors.py
e3sm_quickview/utils/compute.py
e3sm_quickview/utils/constants.py
e3sm_quickview/utils/geometry.py
e3sm_quickview/utils/js.py
e3sm_quickview/utils/math.py
e3sm_compareview-1.1.1.dist-info/METADATA
e3sm_compareview-1.1.1.dist-info/WHEEL
e3sm_compareview-1.1.1.dist-info/entry_points.txt
e3sm_compareview-1.1.1.dist-info/licenses/LICENSE
e3sm_compareview-1.1.1.dist-info/RECORD
